carbonara_pyvex/__init__.py
carbonara_pyvex/block.py
carbonara_pyvex/const.py
carbonara_pyvex/enums.py
carbonara_pyvex/errors.py
carbonara_pyvex/expr.py
carbonara_pyvex/stmt.py
carbonara_pyvex/vex_ffi.py
carbonara_pyvex/include/libvex.h
carbonara_pyvex/include/libvex_basictypes.h
carbonara_pyvex/include/libvex_emnote.h
carbonara_pyvex/include/libvex_guest_amd64.h
carbonara_pyvex/include/libvex_guest_arm.h
carbonara_pyvex/include/libvex_guest_arm64.h
carbonara_pyvex/include/libvex_guest_mips32.h
carbonara_pyvex/include/libvex_guest_mips64.h
carbonara_pyvex/include/libvex_guest_offsets.h
carbonara_pyvex/include/libvex_guest_ppc32.h
carbonara_pyvex/include/libvex_guest_ppc64.h
carbonara_pyvex/include/libvex_guest_s390x.h
carbonara_pyvex/include/libvex_guest_tilegx.h
carbonara_pyvex/include/libvex_guest_x86.h
carbonara_pyvex/include/libvex_ir.h
carbonara_pyvex/include/libvex_s390x_common.h
carbonara_pyvex/include/libvex_trc_values.h
carbonara_pyvex/include/pyvex.h
carbonara_pyvex/lib/libpyvex.a
carbonara_pyvex/lib/libpyvex.so
carbonara_pyvex/lift/__init__.py
carbonara_pyvex/lift/fixes.py
carbonara_pyvex/lift/libvex.py
carbonara_pyvex/lift/util/__init__.py
carbonara_pyvex/lift/util/instr_helper.py
carbonara_pyvex/lift/util/irsb_postprocess.py
carbonara_pyvex/lift/util/lifter_helper.py
carbonara_pyvex/lift/util/syntax_wrapper.py
carbonara_pyvex/lift/util/vex_helper.py
carbonara_pyvex-7.7.9.14.post3.dist-info/DESCRIPTION.rst
carbonara_pyvex-7.7.9.14.post3.dist-info/METADATA
carbonara_pyvex-7.7.9.14.post3.dist-info/RECORD
carbonara_pyvex-7.7.9.14.post3.dist-info/WHEEL
carbonara_pyvex-7.7.9.14.post3.dist-info/metadata.json
carbonara_pyvex-7.7.9.14.post3.dist-info/top_level.txt
