Metadata-Version: 2.0
Name: carbonara-pyvex
Version: 7.7.9.14-3
Summary: Python bindings for Valgrind's VEX IR. Forked from UCSB PyVex to be used in Guanciale.
Home-page: https://github.com/Carbonara-Project/Carbonara-PyVEX
Author: UNKNOWN
Author-email: UNKNOWN
License: UNKNOWN
Platform: UNKNOWN
Requires-Dist: pycparser
Requires-Dist: cffi (>=1.0.3)
Requires-Dist: carbonara-archinfo
Requires-Dist: bitstring
